LatinSquareSolver/latinSquare.py
LatinSquareSolver/solver.py
LatinSquareSolver/__init__.py
LatinSquareSolver/dataCollector.py
LatinSquareSolver-1.0.1.dist-info/RECORD
LatinSquareSolver-1.0.1.dist-info/top_level.txt
LatinSquareSolver-1.0.1.dist-info/metadata.json
LatinSquareSolver-1.0.1.dist-info/WHEEL
LatinSquareSolver-1.0.1.dist-info/METADATA
LatinSquareSolver-1.0.1.dist-info/DESCRIPTION.rst
